{
  "_class": "group",
  "booleanOperation": -1,
  "clippingMaskMode": 0,
  "do_objectID": "1BBE2F0D-5C38-40B7-B2D6-47CD0ACAC7F8",
  "exportOptions": {
    "_class": "exportOptions",
    "do_objectID": "F33B56ED-CFE1-443B-9909-D699A183B873",
    "exportFormats": [
    ],
    "includedLayerIds": [
    ],
    "layerOptions": 0,
    "shouldTrim": false
  },
  "frame": {
    "_class": "rect",
    "constrainProportions": false,
    "do_objectID": "4572C610-B0DA-410B-B00E-8E94F0DC9D18",
    "height": 821,
    "width": 1440,
    "x": 0,
    "y": 1084
  },
  "groupLayout": {
    "_class": "MSImmutableFreeformGroupLayout",
    "do_objectID": "C41EA7D5-7E90-4BA2-B7F5-B931A4A18191"
  },
  "hasClickThrough": false,
  "hasClippingMask": false,
  "isFixedToViewport": false,
  "isFlippedHorizontal": false,
  "isFlippedVertical": false,
  "isLocked": false,
  "isVisible": true,
  "layerListExpandedType": 2,
  "layers": [
    {
      "class": "group",
      "id": "F21DF1F0-3C7D-4CBF-95CF-7CE5EEDE045A"
    }
  ],
  "name": "Group 6",
  "nameIsFixed": false,
  "resizingConstraint": 63,
  "resizingType": 0,
  "rotation": 0,
  "shouldBreakMaskChain": false,
  "style": {
    "_class": "style",
    "do_objectID": "100111FF-D6F0-4528-98F8-EBB7D5D19441",
    "endMarkerType": 0,
    "miterLimit": 10,
    "startMarkerType": 0,
    "windingRule": 1
  }
}