{
  "_class": "shapeGroup",
  "booleanOperation": 0,
  "clippingMaskMode": 0,
  "do_objectID": "2B2358AA-20CA-4BAF-9C2B-02A0025FBE14",
  "exportOptions": {
    "_class": "exportOptions",
    "do_objectID": "A3F4FD19-C992-4B80-ADF7-D4DCCE5A1DEB",
    "exportFormats": [
    ],
    "includedLayerIds": [
    ],
    "layerOptions": 0,
    "shouldTrim": false
  },
  "frame": {
    "_class": "rect",
    "constrainProportions": false,
    "do_objectID": "89E00E14-4085-4B3A-B5BE-1C2DC17FE337",
    "height": 34.49467185624599,
    "width": 37.99999999999989,
    "x": 0.709999999999809,
    "y": 0.885328143753668
  },
  "groupLayout": {
    "_class": "MSImmutableFreeformGroupLayout",
    "do_objectID": "E2954B25-2C4E-4650-B9A9-EBE463A3C49E"
  },
  "hasClickThrough": false,
  "hasClippingMask": false,
  "isFixedToViewport": false,
  "isFlippedHorizontal": false,
  "isFlippedVertical": false,
  "isLocked": false,
  "isVisible": true,
  "layerListExpandedType": 1,
  "layers": [
    {
      "class": "shapePath",
      "id": "D9042FBA-036F-498F-A985-E7069094B40A"
    },
    {
      "class": "shapePath",
      "id": "1528F973-4E30-48D3-9926-EFC29664CA5E"
    },
    {
      "class": "shapePath",
      "id": "5E274B82-CD05-44CF-B5C2-B5872F38D7E9"
    },
    {
      "class": "shapePath",
      "id": "D44F2A3F-6F4A-4526-864C-8BF3FC09BFCC"
    }
  ],
  "name": "Shape",
  "nameIsFixed": false,
  "resizingConstraint": 63,
  "resizingType": 0,
  "rotation": 0,
  "shouldBreakMaskChain": false,
  "style": {
    "_class": "style",
    "do_objectID": "D81F27C8-109B-4B58-8EB6-A8968DE7AAF7",
    "endMarkerType": 0,
    "fills": [
      {
        "_class": "fill",
        "color": {
          "_class": "color",
          "alpha": 1,
          "blue": 0,
          "green": 0,
          "red": 0
        },
        "fillType": 0,
        "isEnabled": true,
        "noiseIndex": 0,
        "noiseIntensity": 0,
        "patternFillType": 1,
        "patternTileScale": 1
      }
    ],
    "miterLimit": 10,
    "startMarkerType": 0,
    "windingRule": 1
  },
  "windingRule": 1
}