{
  "_class": "group",
  "booleanOperation": -1,
  "clippingMaskMode": 0,
  "do_objectID": "A56A730C-E17F-4CF9-8B56-F1099C80D445",
  "exportOptions": {
    "_class": "exportOptions",
    "do_objectID": "FAC204AA-9E97-41DF-A54F-0A8A1AA584C6",
    "exportFormats": [
    ],
    "includedLayerIds": [
    ],
    "layerOptions": 0,
    "shouldTrim": false
  },
  "frame": {
    "_class": "rect",
    "constrainProportions": false,
    "do_objectID": "C15311C0-76B8-4588-9AF7-0D757F29AF56",
    "height": 36,
    "width": 217,
    "x": 16,
    "y": 278
  },
  "groupLayout": {
    "_class": "MSImmutableInferredGroupLayout",
    "axis": 1,
    "do_objectID": "98BEDA2D-DFE0-4707-A5BD-CEB8FC3614D0",
    "layoutAnchor": 1
  },
  "hasClickThrough": false,
  "hasClippingMask": false,
  "isFixedToViewport": false,
  "isFlippedHorizontal": false,
  "isFlippedVertical": false,
  "isLocked": false,
  "isVisible": true,
  "layerListExpandedType": 2,
  "layers": [
    {
      "class": "group",
      "id": "AA6A542C-333C-44B8-B291-2641C718789D"
    }
  ],
  "name": "Text",
  "nameIsFixed": true,
  "resizingConstraint": 42,
  "resizingType": 0,
  "rotation": 0,
  "shouldBreakMaskChain": false,
  "style": {
    "_class": "style",
    "borderOptions": {
      "_class": "borderOptions",
      "dashPattern": [
      ],
      "do_objectID": "F8FBDD90-7FA3-48E9-BF32-9CEFE8143905",
      "isEnabled": true,
      "lineCapStyle": 0,
      "lineJoinStyle": 0
    },
    "colorControls": {
      "_class": "colorControls",
      "brightness": 0,
      "contrast": 1,
      "do_objectID": "0748E9FC-8521-4185-B721-BF63F6D09147",
      "hue": 0,
      "isEnabled": true,
      "saturation": 1
    },
    "do_objectID": "D106B30C-0E31-4A7A-AE5A-7D69095DF1B2",
    "endMarkerType": 0,
    "miterLimit": 10,
    "startMarkerType": 0,
    "windingRule": 1
  },
  "userInfo": {
    "com.animaapp.stc-sketch-plugin": {
      "kModelPropertiesKey": {
        "constraints": {
          "automatic": 1,
          "centerVertically": {
            "constant": 0,
            "enabled": 1,
            "modelID": "constraint_4145fefe-0bbf-4b6d-9fc8-544a8e9d456d",
            "model_class": "ADModelConstraint",
            "model_version": 0,
            "multiplier": 0
          },
          "modelID": "viewConstraints_6b116e67-5e16-4f5d-b288-278a03254f50",
          "model_class": "ADModelViewConstraints",
          "model_version": 0,
          "scaleFactor": 1
        }
      }
    }
  }
}