{
  "_class": "symbolInstance",
  "booleanOperation": -1,
  "clippingMaskMode": 0,
  "do_objectID": "DC50FFF2-BDD9-4C76-A4CE-DE688A524A30",
  "exportOptions": {
    "_class": "exportOptions",
    "do_objectID": "0B9D63CF-6E6B-46CC-B66F-7514F76A0283",
    "exportFormats": [
    ],
    "includedLayerIds": [
    ],
    "layerOptions": 0,
    "shouldTrim": false
  },
  "frame": {
    "_class": "rect",
    "constrainProportions": false,
    "do_objectID": "F92EE38A-93CF-4413-9720-7547977EFEC8",
    "height": 28,
    "width": 82.15625,
    "x": 72.8203125,
    "y": 0
  },
  "hasClippingMask": false,
  "horizontalSpacing": 0,
  "isFixedToViewport": false,
  "isFlippedHorizontal": false,
  "isFlippedVertical": false,
  "isLocked": false,
  "isVisible": true,
  "layerListExpandedType": 0,
  "name": "Tag 2",
  "nameIsFixed": false,
  "overrideValues": [
    {
      "_class": "overrideValue",
      "overrideName": "7C2A3615-8D8F-4EB5-B525-51747BEDC583_stringValue",
      "value": "Subcategory"
    }
  ],
  "resizingConstraint": 63,
  "resizingType": 0,
  "rotation": 0,
  "scale": 1,
  "shouldBreakMaskChain": false,
  "style": {
    "_class": "style",
    "borderOptions": {
      "_class": "borderOptions",
      "dashPattern": [
      ],
      "do_objectID": "7149445C-E6A4-4A72-AB83-85D694B1A3D7",
      "isEnabled": true,
      "lineCapStyle": 0,
      "lineJoinStyle": 0
    },
    "colorControls": {
      "_class": "colorControls",
      "brightness": 0,
      "contrast": 1,
      "do_objectID": "87390B70-1DE9-4EBE-AC2E-4ED5837B1F84",
      "hue": 0,
      "isEnabled": true,
      "saturation": 1
    },
    "do_objectID": "6B2DD121-1DC1-4E88-83DB-C74A7522F530",
    "endMarkerType": 0,
    "miterLimit": 10,
    "startMarkerType": 0,
    "windingRule": 1
  },
  "symbolID": "696A587A-679C-484A-9B4D-E15673EC54A1",
  "verticalSpacing": 0
}