{
  "_class": "artboard",
  "backgroundColor": {
    "_class": "color",
    "alpha": 1,
    "blue": 1,
    "do_objectID": "703A6EDC-8DC1-4B76-9DB6-D3C3F83B56E0",
    "green": 1,
    "red": 1
  },
  "booleanOperation": -1,
  "clippingMaskMode": 0,
  "do_objectID": "75271CB4-6BAE-4BEC-84E3-1E37A9CE5811",
  "exportOptions": {
    "_class": "exportOptions",
    "do_objectID": "7E37B468-BAEB-412C-A2EB-CD2B99015283",
    "exportFormats": [
    ],
    "includedLayerIds": [
    ],
    "layerOptions": 0,
    "shouldTrim": false
  },
  "frame": {
    "_class": "rect",
    "constrainProportions": false,
    "do_objectID": "1136D681-FDD9-4FCF-ACD7-7E8EA4A35DFB",
    "height": 1714,
    "width": 1440,
    "x": -2456,
    "y": -15895
  },
  "groupLayout": {
    "_class": "MSImmutableFreeformGroupLayout",
    "do_objectID": "43CF79F3-8A0D-4AD0-929E-0C7FFF508B14"
  },
  "hasBackgroundColor": true,
  "hasClickThrough": true,
  "hasClippingMask": false,
  "horizontalRulerData": {
    "_class": "rulerData",
    "base": 0,
    "do_objectID": "A33C957F-1954-4C75-BE3C-0D5B40812D09",
    "guides": [
    ]
  },
  "includeBackgroundColorInExport": true,
  "includeInCloudUpload": true,
  "isFixedToViewport": false,
  "isFlippedHorizontal": false,
  "isFlippedVertical": false,
  "isFlowHome": false,
  "isLocked": false,
  "isVisible": true,
  "layerListExpandedType": 0,
  "layers": [
    {
      "class": "text",
      "id": "CEB118CE-3738-4C66-9088-683F909E8848"
    },
    {
      "class": "group",
      "id": "94DE1EBF-3267-42F1-8335-F55F850FA033"
    },
    {
      "class": "group",
      "id": "71A70519-0595-428C-BD35-47168E9ABA02"
    },
    {
      "class": "group",
      "id": "77BE2EF6-C18E-4CC5-AA86-7BCCC1125FD7"
    },
    {
      "class": "group",
      "id": "F2DC2198-7C13-4F6D-B1CE-5905F3189818"
    },
    {
      "class": "group",
      "id": "DEDBD2AC-AA09-4D37-B639-9BB2BEAE5040"
    }
  ],
  "layout": {
    "_class": "layoutGrid",
    "columnWidth": 65,
    "do_objectID": "476A1946-D171-42B5-BD12-359526C9E741",
    "drawHorizontal": false,
    "drawHorizontalLines": false,
    "drawVertical": true,
    "gutterHeight": 12,
    "gutterWidth": 30,
    "guttersOutside": false,
    "horizontalOffset": 165,
    "isEnabled": false,
    "numberOfColumns": 12,
    "rowHeightMultiplication": 5,
    "totalWidth": 1110
  },
  "name": "login step 1",
  "nameIsFixed": true,
  "presetDictionary": {
    "allowResizedMatching": 0,
    "height": 1024,
    "name": "Desktop HD",
    "offersLandscapeVariant": 0,
    "width": 1440
  },
  "resizesContent": false,
  "resizingConstraint": 63,
  "resizingType": 0,
  "rotation": 0,
  "shouldBreakMaskChain": true,
  "style": {
    "_class": "style",
    "do_objectID": "25355405-A648-4663-A72E-6F0D33817B12",
    "endMarkerType": 0,
    "miterLimit": 10,
    "startMarkerType": 0,
    "windingRule": 1
  },
  "verticalRulerData": {
    "_class": "rulerData",
    "base": 0,
    "do_objectID": "BA15818D-609F-42A0-BDC0-F61BA966E5E1",
    "guides": [
    ]
  }
}