{
  "_class": "symbolInstance",
  "booleanOperation": -1,
  "clippingMaskMode": 0,
  "do_objectID": "FDD52259-463F-4B87-BB8A-22E8841FC777",
  "exportOptions": {
    "_class": "exportOptions",
    "do_objectID": "46F3298C-345A-4C50-A96A-B3362CD18E04",
    "exportFormats": [
    ],
    "includedLayerIds": [
    ],
    "layerOptions": 0,
    "shouldTrim": false
  },
  "frame": {
    "_class": "rect",
    "constrainProportions": false,
    "do_objectID": "A5E46DBD-EB64-49D6-83CE-DF0AD4AE18EC",
    "height": 24,
    "width": 24,
    "x": 88,
    "y": 0
  },
  "hasClippingMask": false,
  "horizontalSpacing": 0,
  "isFixedToViewport": false,
  "isFlippedHorizontal": false,
  "isFlippedVertical": false,
  "isLocked": false,
  "isVisible": true,
  "layerListExpandedType": 0,
  "name": "icons / chevron-down copy",
  "nameIsFixed": false,
  "overrideValues": [
    {
      "_class": "overrideValue",
      "overrideName": "CC42F954-0209-4983-8196-9C03A22A2BA1_symbolID",
      "value": "3B7D4BF4-0C9B-4E2D-876A-9CE11118D415"
    }
  ],
  "resizingConstraint": 63,
  "resizingType": 0,
  "rotation": 0,
  "scale": 1,
  "shouldBreakMaskChain": false,
  "style": {
    "_class": "style",
    "do_objectID": "8FAC6318-95C6-403F-B9F4-455719414C50",
    "endMarkerType": 0,
    "miterLimit": 10,
    "startMarkerType": 0,
    "windingRule": 1
  },
  "symbolID": "66441486-70FD-44FA-ADB2-BD880AC9E10D",
  "verticalSpacing": 0
}