{
  "_class": "text",
  "attributedString": {
    "_class": "attributedString",
    "attributes": [
      {
        "_class": "stringAttribute",
        "attributes": {
          "MSAttributedStringColorAttribute": {
            "_class": "color",
            "alpha": 1,
            "blue": 0.1607843137254902,
            "green": 0.04313725490196078,
            "red": 0.08627450980392162
          },
          "MSAttributedStringFontAttribute": {
            "_class": "UIFontDescriptor",
            "attributes": {
              "name": "SharpSansNo1-Bold",
              "size": 35
            }
          },
          "kerning": 0,
          "paragraphStyle": {
            "_class": "paragraphStyle",
            "alignment": 0,
            "baseWritingDirection": 0,
            "maximumLineHeight": 40,
            "minimumLineHeight": 40
          },
          "textStyleVerticalAlignmentKey": 0
        },
        "length": 15,
        "location": 0
      }
    ],
    "string": "Select Catagory"
  },
  "automaticallyDrawOnUnderlyingPath": false,
  "booleanOperation": -1,
  "clippingMaskMode": 0,
  "do_objectID": "7A6597B3-9FA0-4D97-8388-CAE85B58D58D",
  "dontSynchroniseWithSymbol": false,
  "exportOptions": {
    "_class": "exportOptions",
    "do_objectID": "86E269DC-294D-4D1B-A611-97065C846ABF",
    "exportFormats": [
    ],
    "includedLayerIds": [
    ],
    "layerOptions": 0,
    "shouldTrim": false
  },
  "frame": {
    "_class": "rect",
    "constrainProportions": false,
    "do_objectID": "566670E2-795B-4D29-B9DA-D185B0B89109",
    "height": 40,
    "width": 348,
    "x": 0,
    "y": 5
  },
  "glyphBounds": "{{0, 9}, {259, 35}}",
  "hasClippingMask": false,
  "isFixedToViewport": false,
  "isFlippedHorizontal": false,
  "isFlippedVertical": false,
  "isLocked": false,
  "isVisible": true,
  "layerListExpandedType": 0,
  "lineSpacingBehaviour": 2,
  "name": "Select Catagory",
  "nameIsFixed": false,
  "resizingConstraint": 63,
  "resizingType": 0,
  "rotation": 0,
  "sharedStyleID": "1AA3EA47-77CA-46A4-BC49-9392151B4550",
  "shouldBreakMaskChain": false,
  "style": {
    "_class": "style",
    "do_objectID": "BAC8B4E5-E21B-489E-9FD1-D7D5E954A324",
    "endMarkerType": 0,
    "miterLimit": 10,
    "startMarkerType": 0,
    "textStyle": {
      "_class": "textStyle",
      "do_objectID": "60C38CA4-C73D-489F-9FAB-1FF3A5B67504",
      "encodedAttributes": {
        "MSAttributedStringColorAttribute": {
          "_class": "color",
          "alpha": 1,
          "blue": 0.1607843137254902,
          "green": 0.04313725490196078,
          "red": 0.08627450980392162
        },
        "MSAttributedStringFontAttribute": {
          "_class": "UIFontDescriptor",
          "attributes": {
            "name": "SharpSansNo1-Bold",
            "size": 35
          }
        },
        "kerning": 0,
        "paragraphStyle": {
          "_class": "paragraphStyle",
          "alignment": 0,
          "baseWritingDirection": 0,
          "maximumLineHeight": 40,
          "minimumLineHeight": 40
        },
        "textStyleVerticalAlignmentKey": 0
      },
      "verticalAlignment": 0
    },
    "windingRule": 1
  },
  "textBehaviour": 1
}