{
  "_class": "group",
  "booleanOperation": -1,
  "clippingMaskMode": 0,
  "do_objectID": "FC5FF1DF-B745-4A1A-A9FE-0112BB99A035",
  "exportOptions": {
    "_class": "exportOptions",
    "do_objectID": "3DBF58DE-072C-40F5-9BCC-2C1BB3974DB6",
    "exportFormats": [
    ],
    "includedLayerIds": [
    ],
    "layerOptions": 0,
    "shouldTrim": false
  },
  "frame": {
    "_class": "rect",
    "constrainProportions": false,
    "do_objectID": "141BDDE0-F9EB-4B10-A1C4-B05A648C2DED",
    "height": 190,
    "width": 256,
    "x": 0,
    "y": 0
  },
  "groupLayout": {
    "_class": "MSImmutableFreeformGroupLayout",
    "do_objectID": "5C6A2DC0-7F99-4F28-9858-6D4428D5D2E8"
  },
  "hasClickThrough": false,
  "hasClippingMask": false,
  "isFixedToViewport": false,
  "isFlippedHorizontal": false,
  "isFlippedVertical": false,
  "isLocked": false,
  "isVisible": true,
  "layerListExpandedType": 2,
  "layers": [
    {
      "class": "rectangle",
      "id": "31E49382-F51F-4ED7-A348-4B023A91207B"
    },
    {
      "class": "group",
      "id": "39B7BCAE-2543-4DDD-BCB9-F283DC9E6162"
    }
  ],
  "name": "Group 9",
  "nameIsFixed": false,
  "resizingConstraint": 63,
  "resizingType": 0,
  "rotation": 0,
  "shouldBreakMaskChain": false,
  "style": {
    "_class": "style",
    "do_objectID": "90A19D41-2820-41B7-B142-1AA1543847A3",
    "endMarkerType": 0,
    "miterLimit": 10,
    "startMarkerType": 0,
    "windingRule": 1
  }
}