{
  "_class": "group",
  "booleanOperation": -1,
  "clippingMaskMode": 0,
  "do_objectID": "4F95135C-54EE-4FB7-8CB2-1051E8822D47",
  "exportOptions": {
    "_class": "exportOptions",
    "do_objectID": "102C8B47-3DD7-4EE5-82A9-4B77197128A4",
    "exportFormats": [
    ],
    "includedLayerIds": [
    ],
    "layerOptions": 0,
    "shouldTrim": false
  },
  "frame": {
    "_class": "rect",
    "constrainProportions": false,
    "do_objectID": "99DE7AFC-4E84-4EC9-BD9A-35E918710C34",
    "height": 132,
    "width": 223,
    "x": 16,
    "y": 168
  },
  "groupLayout": {
    "_class": "MSImmutableInferredGroupLayout",
    "axis": 1,
    "do_objectID": "B9E6FAAA-2C40-4A9C-8109-2575D432E235",
    "layoutAnchor": 0
  },
  "hasClickThrough": false,
  "hasClippingMask": false,
  "isFixedToViewport": false,
  "isFlippedHorizontal": false,
  "isFlippedVertical": false,
  "isLocked": false,
  "isVisible": true,
  "layerListExpandedType": 0,
  "layers": [
    {
      "class": "text",
      "id": "A20A6814-607C-4304-B160-AFE89C3F82A7"
    },
    {
      "class": "symbolInstance",
      "id": "90B5B5FA-49AA-41C5-9DDD-DDE2778A8CF0"
    },
    {
      "class": "text",
      "id": "89FB5223-922F-49BC-BD1B-458FFC168BB2"
    }
  ],
  "name": "Text",
  "nameIsFixed": true,
  "resizingConstraint": 10,
  "resizingType": 0,
  "rotation": 0,
  "shouldBreakMaskChain": false,
  "style": {
    "_class": "style",
    "borderOptions": {
      "_class": "borderOptions",
      "dashPattern": [
      ],
      "do_objectID": "2D199768-8A63-4D03-ACEE-F4356D5FE779",
      "isEnabled": true,
      "lineCapStyle": 0,
      "lineJoinStyle": 0
    },
    "colorControls": {
      "_class": "colorControls",
      "brightness": 0,
      "contrast": 1,
      "do_objectID": "C5A73173-CF92-4E66-B0B9-D5FAE6575681",
      "hue": 0,
      "isEnabled": true,
      "saturation": 1
    },
    "do_objectID": "00046E22-2C56-4DFA-91F5-736F31846833",
    "endMarkerType": 0,
    "miterLimit": 10,
    "startMarkerType": 0,
    "windingRule": 1
  }
}