{
  "_class": "text",
  "attributedString": {
    "_class": "attributedString",
    "attributes": [
      {
        "_class": "stringAttribute",
        "attributes": {
          "MSAttributedStringColorAttribute": {
            "_class": "color",
            "alpha": 1,
            "blue": 0.6379076086956522,
            "green": 0.6379076086956522,
            "red": 0.6379076086956522
          },
          "MSAttributedStringFontAttribute": {
            "_class": "UIFontDescriptor",
            "attributes": {
              "name": "SharpSansNo1-Bold",
              "size": 22
            }
          },
          "paragraphStyle": {
            "_class": "paragraphStyle",
            "alignment": 0,
            "baseWritingDirection": 0
          },
          "textStyleVerticalAlignmentKey": 0
        },
        "length": 8,
        "location": 0
      }
    ],
    "string": "Progress"
  },
  "automaticallyDrawOnUnderlyingPath": false,
  "booleanOperation": -1,
  "clippingMaskMode": 0,
  "do_objectID": "E4DE247D-C7D0-4E7A-9DC8-6B4E9167C1BA",
  "dontSynchroniseWithSymbol": false,
  "exportOptions": {
    "_class": "exportOptions",
    "do_objectID": "4B2B9D96-E987-4D7E-9F04-464026EB56E7",
    "exportFormats": [
    ],
    "includedLayerIds": [
    ],
    "layerOptions": 0,
    "shouldTrim": false
  },
  "frame": {
    "_class": "rect",
    "constrainProportions": false,
    "do_objectID": "120ECEBC-AFE0-49A5-8E8C-50E94CB6309F",
    "height": 30,
    "width": 88,
    "x": 0,
    "y": 63
  },
  "glyphBounds": "{{0, 7}, {88, 23}}",
  "hasClippingMask": false,
  "isFixedToViewport": false,
  "isFlippedHorizontal": false,
  "isFlippedVertical": false,
  "isLocked": false,
  "isVisible": true,
  "layerListExpandedType": 0,
  "lineSpacingBehaviour": 2,
  "name": "Progress",
  "nameIsFixed": false,
  "resizingConstraint": 47,
  "resizingType": 0,
  "rotation": 0,
  "sharedStyleID": "249153DA-25F9-4D3B-9672-826DFF89DC43",
  "shouldBreakMaskChain": false,
  "style": {
    "_class": "style",
    "do_objectID": "611875BA-E38C-4549-901A-E34522F8A9B0",
    "endMarkerType": 0,
    "miterLimit": 10,
    "startMarkerType": 0,
    "textStyle": {
      "_class": "textStyle",
      "do_objectID": "DE9828FB-4722-4B06-B51F-CC1FD8CB2B95",
      "encodedAttributes": {
        "MSAttributedStringColorAttribute": {
          "_class": "color",
          "alpha": 1,
          "blue": 0.6379076086956522,
          "green": 0.6379076086956522,
          "red": 0.6379076086956522
        },
        "MSAttributedStringFontAttribute": {
          "_class": "UIFontDescriptor",
          "attributes": {
            "name": "SharpSansNo1-Bold",
            "size": 22
          }
        },
        "paragraphStyle": {
          "_class": "paragraphStyle",
          "alignment": 0,
          "baseWritingDirection": 0
        },
        "textStyleVerticalAlignmentKey": 0
      },
      "verticalAlignment": 0
    },
    "windingRule": 1
  },
  "textBehaviour": 0
}