{
  "_class": "group",
  "booleanOperation": -1,
  "clippingMaskMode": 0,
  "do_objectID": "1D6AE223-6AC4-4DEF-A771-49BDF5EBEB63",
  "exportOptions": {
    "_class": "exportOptions",
    "do_objectID": "4EEB0962-9ACC-4538-9494-3EB4B07B082D",
    "exportFormats": [
    ],
    "includedLayerIds": [
    ],
    "layerOptions": 0,
    "shouldTrim": false
  },
  "frame": {
    "_class": "rect",
    "constrainProportions": false,
    "do_objectID": "75D718D8-DE23-42C0-8EE7-783B9FB4E01A",
    "height": 72,
    "width": 255,
    "x": 165,
    "y": 878
  },
  "groupLayout": {
    "_class": "MSImmutableFreeformGroupLayout",
    "do_objectID": "B7FAA115-E1BC-4675-96CA-8847A1B367E1"
  },
  "hasClickThrough": false,
  "hasClippingMask": false,
  "isFixedToViewport": false,
  "isFlippedHorizontal": false,
  "isFlippedVertical": false,
  "isLocked": false,
  "isVisible": true,
  "layerListExpandedType": 0,
  "layers": [
    {
      "class": "symbolInstance",
      "id": "5A98F84C-1FA4-4DB6-B6F0-6C04A7DEE609"
    },
    {
      "class": "group",
      "id": "B99D074A-3B61-4F01-83E3-21D118DE1CE3"
    },
    {
      "class": "group",
      "id": "004CEF7A-6BBF-4E45-92EC-004EAB143700"
    },
    {
      "class": "group",
      "id": "14565FA1-A98B-4FF1-8121-E71A81E7528D"
    }
  ],
  "name": "Card/Blog/Simple Copy 18",
  "nameIsFixed": false,
  "resizingConstraint": 63,
  "resizingType": 0,
  "rotation": 0,
  "shouldBreakMaskChain": false,
  "style": {
    "_class": "style",
    "borderOptions": {
      "_class": "borderOptions",
      "dashPattern": [
      ],
      "do_objectID": "0B2BE9DF-166F-42EF-9D42-C6478813B2F0",
      "isEnabled": true,
      "lineCapStyle": 0,
      "lineJoinStyle": 0
    },
    "colorControls": {
      "_class": "colorControls",
      "brightness": 0,
      "contrast": 1,
      "do_objectID": "5DDBB226-A1AB-465C-B599-05C62A360A34",
      "hue": 0,
      "isEnabled": true,
      "saturation": 1
    },
    "do_objectID": "85141F94-F0BF-4509-9380-20D6F471D76E",
    "endMarkerType": 0,
    "miterLimit": 10,
    "startMarkerType": 0,
    "windingRule": 1
  }
}