{
  "_class": "text",
  "attributedString": {
    "_class": "attributedString",
    "attributes": [
      {
        "_class": "stringAttribute",
        "attributes": {
          "MSAttributedStringColorAttribute": {
            "_class": "color",
            "alpha": 1,
            "blue": 0.2543048469387755,
            "green": 0.2310909003086912,
            "red": 0.217825787948643
          },
          "MSAttributedStringFontAttribute": {
            "_class": "UIFontDescriptor",
            "attributes": {
              "name": "Helvetica-Bold",
              "size": 12
            }
          },
          "kerning": 0.2000000029802322,
          "paragraphStyle": {
            "_class": "paragraphStyle",
            "alignment": 0,
            "allowsDefaultTighteningForTruncation": 0,
            "maximumLineHeight": 16,
            "minimumLineHeight": 16
          }
        },
        "length": 14,
        "location": 0
      }
    ],
    "string": "Dhanushka Dave"
  },
  "automaticallyDrawOnUnderlyingPath": false,
  "booleanOperation": -1,
  "clippingMaskMode": 0,
  "do_objectID": "0450C69C-270A-4398-B512-267C0FE9A6F2",
  "dontSynchroniseWithSymbol": false,
  "exportOptions": {
    "_class": "exportOptions",
    "do_objectID": "EFC79CA6-DDCF-4651-93B3-FBB5EA3153E8",
    "exportFormats": [
    ],
    "includedLayerIds": [
    ],
    "layerOptions": 0,
    "shouldTrim": false
  },
  "frame": {
    "_class": "rect",
    "constrainProportions": false,
    "do_objectID": "8BA9A03E-0466-4321-B5A6-369F5595E23F",
    "height": 16,
    "width": 167,
    "x": 0,
    "y": 0
  },
  "glyphBounds": "{{0, 2}, {99, 10}}",
  "hasClippingMask": false,
  "isFixedToViewport": false,
  "isFlippedHorizontal": false,
  "isFlippedVertical": false,
  "isLocked": false,
  "isVisible": true,
  "layerListExpandedType": 0,
  "lineSpacingBehaviour": 2,
  "name": "Heading",
  "nameIsFixed": false,
  "resizingConstraint": 42,
  "resizingType": 0,
  "rotation": 0,
  "shouldBreakMaskChain": false,
  "style": {
    "_class": "style",
    "borderOptions": {
      "_class": "borderOptions",
      "dashPattern": [
      ],
      "do_objectID": "364A1CC8-7865-4F41-83F1-5561E09C6814",
      "isEnabled": true,
      "lineCapStyle": 0,
      "lineJoinStyle": 0
    },
    "colorControls": {
      "_class": "colorControls",
      "brightness": 0,
      "contrast": 1,
      "do_objectID": "D36DABF0-CFDF-452D-92DB-E9A57C6C4447",
      "hue": 0,
      "isEnabled": true,
      "saturation": 1
    },
    "do_objectID": "7DA62C12-2ACB-4E42-AC64-2B2F2ECFC6D8",
    "endMarkerType": 0,
    "miterLimit": 10,
    "startMarkerType": 0,
    "textStyle": {
      "_class": "textStyle",
      "do_objectID": "54DC3707-8B29-4BEC-A6A2-D34E72687B64",
      "encodedAttributes": {
        "MSAttributedStringColorAttribute": {
          "_class": "color",
          "alpha": 1,
          "blue": 0.2543048469387755,
          "green": 0.2310909003086912,
          "red": 0.217825787948643
        },
        "MSAttributedStringFontAttribute": {
          "_class": "UIFontDescriptor",
          "attributes": {
            "name": "Helvetica-Bold",
            "size": 12
          }
        },
        "kerning": 0.2000000029802322,
        "paragraphStyle": {
          "_class": "paragraphStyle",
          "alignment": 0,
          "allowsDefaultTighteningForTruncation": 0,
          "maximumLineHeight": 16,
          "minimumLineHeight": 16
        }
      },
      "verticalAlignment": 0
    },
    "windingRule": 1
  },
  "textBehaviour": 1,
  "userInfo": {
    "com.animaapp.stc-sketch-plugin": {
      "kModelPropertiesKey": {
        "isAutoWidth": 1
      }
    }
  }
}