{
  "_class": "group",
  "booleanOperation": -1,
  "clippingMaskMode": 0,
  "do_objectID": "F4E9DF59-16B8-46E4-A8CD-69FB9A091743",
  "exportOptions": {
    "_class": "exportOptions",
    "do_objectID": "FCFF4C04-698A-484F-84F1-52223F6F14C4",
    "exportFormats": [
    ],
    "includedLayerIds": [
    ],
    "layerOptions": 0,
    "shouldTrim": false
  },
  "frame": {
    "_class": "rect",
    "constrainProportions": false,
    "do_objectID": "3D04051B-8E4F-4CE8-B649-B77351C06C5F",
    "height": 30,
    "width": 730,
    "x": 0,
    "y": 100
  },
  "groupLayout": {
    "_class": "MSImmutableFreeformGroupLayout",
    "do_objectID": "89E211E2-C9ED-4962-A343-DAB20A82FEFC"
  },
  "hasClickThrough": false,
  "hasClippingMask": false,
  "isFixedToViewport": false,
  "isFlippedHorizontal": false,
  "isFlippedVertical": false,
  "isLocked": false,
  "isVisible": true,
  "layerListExpandedType": 0,
  "layers": [
    {
      "class": "text",
      "id": "138DF260-DCBE-43C2-BEC0-AE810AEFF1BE"
    },
    {
      "class": "group",
      "id": "F657CDE3-911F-4908-9000-579DF9A94976"
    }
  ],
  "name": "Group 9 Copy",
  "nameIsFixed": false,
  "resizingConstraint": 63,
  "resizingType": 0,
  "rotation": 0,
  "shouldBreakMaskChain": false,
  "style": {
    "_class": "style",
    "do_objectID": "12672757-E165-4DEF-A6C2-80AE2582C552",
    "endMarkerType": 0,
    "miterLimit": 10,
    "startMarkerType": 0,
    "windingRule": 1
  }
}