{
  "_class": "shapeGroup",
  "booleanOperation": 0,
  "clippingMaskMode": 0,
  "do_objectID": "29AA8FF2-C442-48CA-93D9-8AA8D3AF1EE4",
  "exportOptions": {
    "_class": "exportOptions",
    "exportFormats": [
    ],
    "includedLayerIds": [
    ],
    "layerOptions": 0,
    "shouldTrim": false
  },
  "frame": {
    "_class": "rect",
    "constrainProportions": false,
    "height": 24,
    "width": 24,
    "x": 0,
    "y": 0
  },
  "groupLayout": {
    "_class": "MSImmutableFreeformGroupLayout"
  },
  "hasClickThrough": false,
  "hasClippingMask": true,
  "isFixedToViewport": false,
  "isFlippedHorizontal": false,
  "isFlippedVertical": false,
  "isLocked": false,
  "isVisible": true,
  "layerListExpandedType": 0,
  "layers": [
    {
      "class": "shapePath",
      "id": "63106775-199D-4DEF-A942-858699651FB2"
    },
    {
      "class": "shapePath",
      "id": "A24EB56C-DF13-427A-97BA-C89CC56BE9EE"
    },
    {
      "class": "shapePath",
      "id": "76E5AA48-C1B8-4BB1-A8B5-8E4A7A982FB5"
    },
    {
      "class": "shapePath",
      "id": "1AF12CB9-C189-44D3-B6C6-754DCCAB92E7"
    },
    {
      "class": "shapePath",
      "id": "E02BF466-F5CE-4FF8-BC2B-06A528B2E571"
    },
    {
      "class": "shapePath",
      "id": "44B49116-9164-43C1-A0AA-7214CD73D14C"
    },
    {
      "class": "shapePath",
      "id": "E4588E5C-1235-4731-BF8A-1D92240B9606"
    },
    {
      "class": "shapePath",
      "id": "5150D51F-939A-4895-AA6C-C4F6CF85C3A7"
    },
    {
      "class": "shapePath",
      "id": "5E600E88-F9B9-4F99-A1C2-936DC65A0769"
    },
    {
      "class": "shapePath",
      "id": "2B6E3E61-D113-4BD1-B467-362DEA7BE8BA"
    },
    {
      "class": "shapePath",
      "id": "A0EF605B-3682-4AC1-8271-19A9918D2B34"
    },
    {
      "class": "shapePath",
      "id": "B88B2184-C56E-480D-B0DC-713C3E1BA8AA"
    }
  ],
  "name": "Combined Shape",
  "nameIsFixed": false,
  "resizingConstraint": 63,
  "resizingType": 0,
  "rotation": 0,
  "shouldBreakMaskChain": false,
  "style": {
    "_class": "style",
    "endMarkerType": 0,
    "fills": [
      {
        "_class": "fill",
        "color": {
          "_class": "color",
          "alpha": 1,
          "blue": 0,
          "green": 0,
          "red": 0
        },
        "fillType": 0,
        "isEnabled": true,
        "noiseIndex": 0,
        "noiseIntensity": 0,
        "patternFillType": 1,
        "patternTileScale": 1
      }
    ],
    "miterLimit": 10,
    "startMarkerType": 0,
    "windingRule": 0
  },
  "windingRule": 0
}