{
  "_class": "text",
  "attributedString": {
    "_class": "attributedString",
    "attributes": [
      {
        "_class": "stringAttribute",
        "attributes": {
          "MSAttributedStringColorAttribute": {
            "_class": "color",
            "alpha": 1,
            "blue": 0.2543048469387755,
            "green": 0.2310909003086912,
            "red": 0.217825787948643
          },
          "MSAttributedStringFontAttribute": {
            "_class": "UIFontDescriptor",
            "attributes": {
              "name": "Helvetica-Bold",
              "size": 12
            }
          },
          "kerning": 0.2000000029802322,
          "paragraphStyle": {
            "_class": "paragraphStyle",
            "alignment": 0,
            "allowsDefaultTighteningForTruncation": 0,
            "maximumLineHeight": 16,
            "minimumLineHeight": 16
          }
        },
        "length": 18,
        "location": 0
      }
    ],
    "string": "border bottom fill"
  },
  "automaticallyDrawOnUnderlyingPath": false,
  "booleanOperation": 0,
  "clippingMaskMode": 0,
  "do_objectID": "92F5937C-B806-4FCA-9672-2FF4DD59C926",
  "dontSynchroniseWithSymbol": false,
  "exportOptions": {
    "_class": "exportOptions",
    "do_objectID": "37305845-1145-4CF3-8475-8E78DF8CCCE2",
    "exportFormats": [
    ],
    "includedLayerIds": [
    ],
    "layerOptions": 0,
    "shouldTrim": false
  },
  "frame": {
    "_class": "rect",
    "constrainProportions": false,
    "do_objectID": "211C5A46-7D65-46B9-AF10-1ABAA22BC5F6",
    "height": 16,
    "width": 103,
    "x": 0,
    "y": 0
  },
  "glyphBounds": "{{0, 2}, {102, 10}}",
  "hasClippingMask": false,
  "isFixedToViewport": false,
  "isFlippedHorizontal": false,
  "isFlippedVertical": false,
  "isLocked": false,
  "isVisible": true,
  "layerListExpandedType": 0,
  "lineSpacingBehaviour": 2,
  "name": "border bottom fill",
  "nameIsFixed": false,
  "resizingConstraint": 47,
  "resizingType": 0,
  "rotation": 0,
  "shouldBreakMaskChain": false,
  "style": {
    "_class": "style",
    "borderOptions": {
      "_class": "borderOptions",
      "dashPattern": [
      ],
      "do_objectID": "0319C74A-8688-4143-8455-1AE0A46F86B5",
      "isEnabled": true,
      "lineCapStyle": 0,
      "lineJoinStyle": 0
    },
    "colorControls": {
      "_class": "colorControls",
      "brightness": 0,
      "contrast": 1,
      "do_objectID": "C01477E6-551F-45E8-92DD-9F515E4591C1",
      "hue": 0,
      "isEnabled": true,
      "saturation": 1
    },
    "do_objectID": "072946D6-4FC1-41FB-B867-19B957CBEF8B",
    "endMarkerType": 0,
    "miterLimit": 10,
    "startMarkerType": 0,
    "textStyle": {
      "_class": "textStyle",
      "do_objectID": "91D23925-E3A9-46C9-8D81-FAA3C010B601",
      "encodedAttributes": {
        "MSAttributedStringColorAttribute": {
          "_class": "color",
          "alpha": 1,
          "blue": 0.2543048469387755,
          "green": 0.2310909003086912,
          "red": 0.217825787948643
        },
        "MSAttributedStringFontAttribute": {
          "_class": "UIFontDescriptor",
          "attributes": {
            "name": "Helvetica-Bold",
            "size": 12
          }
        },
        "kerning": 0.2000000029802322,
        "paragraphStyle": {
          "_class": "paragraphStyle",
          "alignment": 0,
          "allowsDefaultTighteningForTruncation": 0,
          "maximumLineHeight": 16,
          "minimumLineHeight": 16
        }
      },
      "verticalAlignment": 0
    },
    "windingRule": 1
  },
  "textBehaviour": 0
}