{
  "_class": "symbolInstance",
  "booleanOperation": 0,
  "clippingMaskMode": 0,
  "do_objectID": "6356CBF8-665A-4653-8EC5-24DA9AEF90C4",
  "exportOptions": {
    "_class": "exportOptions",
    "exportFormats": [
    ],
    "includedLayerIds": [
    ],
    "layerOptions": 0,
    "shouldTrim": false
  },
  "frame": {
    "_class": "rect",
    "constrainProportions": true,
    "height": 18,
    "width": 18,
    "x": 4,
    "y": 3
  },
  "hasClippingMask": false,
  "horizontalSpacing": 0,
  "isFixedToViewport": false,
  "isFlippedHorizontal": false,
  "isFlippedVertical": false,
  "isLocked": false,
  "isVisible": true,
  "layerListExpandedType": 0,
  "name": "Round",
  "nameIsFixed": false,
  "overrideValues": [
    {
      "_class": "overrideValue",
      "overrideName": "75854B75-2F72-4179-A877-33E1D6830506_symbolID",
      "value": "4263F916-52A4-44F2-BC69-6B44C87F4B8C"
    }
  ],
  "resizingConstraint": 9,
  "resizingType": 0,
  "rotation": 0,
  "scale": 1,
  "shouldBreakMaskChain": false,
  "style": {
    "_class": "style",
    "borderOptions": {
      "_class": "borderOptions",
      "dashPattern": [
      ],
      "isEnabled": true,
      "lineCapStyle": 0,
      "lineJoinStyle": 0
    },
    "colorControls": {
      "_class": "colorControls",
      "brightness": 0,
      "contrast": 1,
      "hue": 0,
      "isEnabled": true,
      "saturation": 1
    },
    "endMarkerType": 0,
    "miterLimit": 10,
    "startMarkerType": 0,
    "windingRule": 1
  },
  "symbolID": "04AB7D00-1A34-4F55-9B95-69E155B8BAA5",
  "userInfo": {
    "com.animaapp.stc-sketch-plugin": {
      "kModelPropertiesKey": {
        "constraints": {
          "aspectRatio": {
            "constant": 18,
            "enabled": 1,
            "modelID": "constraint_544c9e54-0bc0-4600-bf29-583053d9bb14",
            "model_class": "ADModelConstraint",
            "model_version": 0,
            "multiplier": 18
          },
          "automatic": 1,
          "modelID": "viewConstraints_54c235a3-2141-4c66-a332-a9490ae642af",
          "model_class": "ADModelViewConstraints",
          "model_version": 0,
          "scaleFactor": 1
        }
      }
    }
  },
  "verticalSpacing": 0
}