{
  "_class": "shapeGroup",
  "booleanOperation": 0,
  "clippingMaskMode": 0,
  "do_objectID": "431D4899-E357-40F6-9E2E-26D3925D1BBD",
  "exportOptions": {
    "_class": "exportOptions",
    "exportFormats": [
    ],
    "includedLayerIds": [
    ],
    "layerOptions": 0,
    "shouldTrim": false
  },
  "frame": {
    "_class": "rect",
    "constrainProportions": true,
    "height": 100,
    "width": 100,
    "x": 440,
    "y": 220
  },
  "groupLayout": {
    "_class": "MSImmutableFreeformGroupLayout"
  },
  "hasClickThrough": false,
  "hasClippingMask": false,
  "isFixedToViewport": false,
  "isFlippedHorizontal": false,
  "isFlippedVertical": false,
  "isLocked": false,
  "isVisible": true,
  "layerListExpandedType": 0,
  "layers": [
    {
      "class": "shapePath",
      "id": "EFDFF1EC-38B2-4524-ADF2-7AAE5B9971BA"
    },
    {
      "class": "shapePath",
      "id": "54E3672F-40BA-4882-AE3D-37C1976584FE"
    },
    {
      "class": "shapePath",
      "id": "170D6AF8-C35F-4BDE-A09D-1D562DB57F2A"
    },
    {
      "class": "shapePath",
      "id": "3CAC68A6-965E-4A9C-BBD5-91B26A1DB591"
    },
    {
      "class": "shapePath",
      "id": "AD70606F-5ACF-4AD2-A99F-87B54E8B305C"
    }
  ],
  "name": "image icon",
  "nameIsFixed": true,
  "resizingConstraint": 45,
  "resizingType": 0,
  "rotation": 0,
  "shouldBreakMaskChain": false,
  "style": {
    "_class": "style",
    "endMarkerType": 0,
    "fills": [
      {
        "_class": "fill",
        "color": {
          "_class": "color",
          "alpha": 1,
          "blue": 0.5137254901960784,
          "green": 0.5137254901960784,
          "red": 0.5137254901960784
        },
        "fillType": 0,
        "isEnabled": true,
        "noiseIndex": 0,
        "noiseIntensity": 0,
        "patternFillType": 1,
        "patternTileScale": 1
      }
    ],
    "miterLimit": 10,
    "startMarkerType": 0,
    "windingRule": 0
  },
  "windingRule": 0
}